{
  "conditions": [],
  "description": {
    "translate": "trait.gigani.creep_resistant.desc"
  },
  "effects": [
    {
      "type": "silentgear:fireproof"
    },
    {
      "type": "silentgear:number_property_modifier",
      "property_modifiers": {
        "silentgear:durability": {
          "base_multiplier": 0.055,
          "multiply_damage_ratio": true,
          "multiply_original_value": true
        },
        "silentgear:armor_toughness": {
          "base_multiplier": 0.055,
          "multiply_damage_ratio": true,
          "multiply_original_value": true
        },
        "silentgear:magic_armor": {
          "base_multiplier": 0.025,
          "multiply_damage_ratio": true,
          "multiply_original_value": true
        }
      }
    }
  ],
  "max_level": 5,
  "name": {
    "translate": "trait.gigani.creep_resistant"
  }
}
