{
  "type": "silentgear:simple",
  "parent": "silentgear:empty",
  "crafting": {
    "can_salvage": true,
    "categories": [
      "gem",
      "advanced"
    ],
    "gear_type_blacklist": [],
    "ingredient": {
      "tag": "c:ingots/crystal_matrix"
    },
    "part_substitutes": {}
  },
  "display": {
    "color": "#FFD57296",
    "main_texture_type": "HIGH_CONTRAST",
    "name": {
      "translate": "material.gigani.crystal_matrix"
    },
    "name_prefix": ""
  },
  "properties": {
    "silentgear:main": {
      "armor": 17.1,
      "armor/boots": 2.4,
      "armor/chestplate": 6.5,
      "armor/helmet": 2.9,
      "armor/leggings": 5.3,
      "armor_durability": 34.4,
      "armor_toughness": 4.6,
      "attack_damage": 4.3,
      "attack_speed": 0,
      "charging_value": 0,
      "draw_speed": 0,
      "durability": 1439.3,
      "enchantment_value": 41,
      "harvest_speed": 9.5,
      "harvest_tier": {
        "incorrect_blocks_for_tool": "minecraft:incorrect_for_diamond_tool",
        "level_hint": "3",
        "name": "diamond"
      },
      "magic_armor": 5.4,
      "magic_damage": 7,
      "projectile_accuracy": 1.21,
      "projectile_speed": 1.03,
      "ranged_damage": 3.7,
      "rarity": 75,
      "repair_value": 0.14,
      "traits": [
        {
          "conditions": [],
          "level": 2,
          "trait": "gigani:resonant_lattice"
        },
        {
          "conditions": [],
          "level": 3,
          "trait": "gigani:crystalline_focus"
        },
        {
          "conditions": [],
          "level": 1,
          "trait": "gigani:brittle_cleavage"
        },
        {
          "conditions": [],
          "level": 2,
          "trait": "gigani:waveform_harmonics"
        },
        {
          "conditions": [],
          "level": 2,
          "trait": "gigani:piezoelectric"
        },
        {
          "conditions": [],
          "level": 2,
          "trait": "gigani:matrix_bound"
        },
        {
          "conditions": [],
          "level": 1,
          "trait": "gigani:resonance_tuned"
        }
      ]
    },
    "silentgear:rod": {
      "durability": {
        "operation": "MULTIPLY_TOTAL",
        "value": 0.117
      },
      "harvest_speed": {
        "operation": "MULTIPLY_TOTAL",
        "value": 0.076
      },
      "traits": [
        {
          "conditions": [],
          "level": 2,
          "trait": "gigani:resonant_lattice"
        },
        {
          "conditions": [],
          "level": 3,
          "trait": "gigani:crystalline_focus"
        },
        {
          "conditions": [],
          "level": 1,
          "trait": "gigani:brittle_cleavage"
        },
        {
          "conditions": [],
          "level": 2,
          "trait": "gigani:matrix_bound"
        },
        {
          "conditions": [],
          "level": 1,
          "trait": "gigani:resonance_tuned"
        }
      ],
      "attack_speed": {
        "operation": "ADD",
        "value": -0.023
      },
      "draw_speed": {
        "operation": "MULTIPLY_TOTAL",
        "value": 0.021
      }
    },
    "silentgear:tip": {
      "armor_durability": {
        "operation": "ADD",
        "value": 4.82
      },
      "attack_damage": {
        "operation": "ADD",
        "value": 1.26
      },
      "durability": {
        "operation": "ADD",
        "value": 221.185
      },
      "harvest_speed": {
        "operation": "ADD",
        "value": 1.621
      },
      "harvest_tier": {
        "incorrect_blocks_for_tool": "minecraft:incorrect_for_diamond_tool",
        "level_hint": "3",
        "name": "diamond"
      },
      "magic_damage": {
        "operation": "ADD",
        "value": 3.324
      },
      "ranged_damage": {
        "operation": "ADD",
        "value": 1.049
      },
      "rarity": {
        "operation": "ADD",
        "value": 18
      },
      "traits": [
        {
          "conditions": [],
          "level": 1,
          "trait": "gigani:brittle_cleavage"
        },
        {
          "conditions": [],
          "level": 2,
          "trait": "gigani:resonant_lattice"
        },
        {
          "conditions": [],
          "level": 3,
          "trait": "gigani:crystalline_focus"
        },
        {
          "conditions": [],
          "level": 2,
          "trait": "gigani:waveform_harmonics"
        },
        {
          "conditions": [],
          "level": 2,
          "trait": "gigani:matrix_bound"
        },
        {
          "conditions": [],
          "level": 1,
          "trait": "gigani:resonance_tuned"
        }
      ]
    },
    "silentgear:coating": {
      "armor_durability": {
        "operation": "MULTIPLY_TOTAL",
        "value": 0.053
      },
      "armor_toughness": {
        "operation": "ADD",
        "value": 1.176
      },
      "durability": {
        "operation": "MULTIPLY_TOTAL",
        "value": 0.113
      },
      "enchantment_value": {
        "operation": "ADD",
        "value": 4
      },
      "harvest_speed": {
        "operation": "MULTIPLY_TOTAL",
        "value": 0.012
      },
      "magic_armor": {
        "operation": "ADD",
        "value": 1.303
      },
      "magic_damage": {
        "operation": "ADD",
        "value": 2
      },
      "ranged_damage": {
        "operation": "MULTIPLY_TOTAL",
        "value": 0.107
      },
      "traits": [
        {
          "conditions": [],
          "level": 2,
          "trait": "gigani:resonant_lattice"
        },
        {
          "conditions": [],
          "level": 3,
          "trait": "gigani:crystalline_focus"
        },
        {
          "conditions": [],
          "level": 1,
          "trait": "gigani:brittle_cleavage"
        },
        {
          "conditions": [],
          "level": 2,
          "trait": "gigani:waveform_harmonics"
        },
        {
          "conditions": [],
          "level": 2,
          "trait": "gigani:matrix_bound"
        },
        {
          "conditions": [],
          "level": 1,
          "trait": "gigani:resonance_tuned"
        }
      ]
    },
    "silentgear:binding": {
      "armor_durability": {
        "operation": "MULTIPLY_BASE",
        "value": 0.097
      },
      "harvest_speed": {
        "operation": "MULTIPLY_BASE",
        "value": 0.012
      },
      "repair_efficiency": {
        "operation": "MULTIPLY_BASE",
        "value": 0.086
      },
      "traits": [
        {
          "conditions": [],
          "level": 2,
          "trait": "gigani:resonant_lattice"
        },
        {
          "conditions": [],
          "level": 3,
          "trait": "gigani:crystalline_focus"
        },
        {
          "conditions": [],
          "level": 1,
          "trait": "gigani:brittle_cleavage"
        },
        {
          "conditions": [],
          "level": 2,
          "trait": "gigani:waveform_harmonics"
        },
        {
          "conditions": [],
          "level": 2,
          "trait": "gigani:matrix_bound"
        },
        {
          "conditions": [],
          "level": 1,
          "trait": "gigani:resonance_tuned"
        }
      ],
      "magic_armor": {
        "operation": "ADD",
        "value": 0.863
      },
      "magic_damage": {
        "operation": "ADD",
        "value": 0.838
      },
      "attack_speed": {
        "operation": "ADD",
        "value": 0.019
      }
    },
    "silentgear:grip": {
      "attack_speed": {
        "operation": "ADD",
        "value": 0.019
      },
      "harvest_speed": {
        "operation": "MULTIPLY_BASE",
        "value": 0.095
      },
      "repair_efficiency": {
        "operation": "MULTIPLY_BASE",
        "value": 0.032
      },
      "traits": [
        {
          "conditions": [],
          "level": 2,
          "trait": "gigani:resonant_lattice"
        },
        {
          "conditions": [],
          "level": 3,
          "trait": "gigani:crystalline_focus"
        },
        {
          "conditions": [],
          "level": 1,
          "trait": "gigani:brittle_cleavage"
        },
        {
          "conditions": [],
          "level": 2,
          "trait": "gigani:waveform_harmonics"
        },
        {
          "conditions": [],
          "level": 2,
          "trait": "gigani:matrix_bound"
        },
        {
          "conditions": [],
          "level": 1,
          "trait": "gigani:resonance_tuned"
        }
      ]
    },
    "silentgear:setting": {
      "enchantment_value": {
        "operation": "ADD",
        "value": 5.936
      },
      "magic_armor": {
        "operation": "ADD",
        "value": 0.971
      },
      "magic_damage": {
        "operation": "ADD",
        "value": 1.688
      },
      "traits": [
        {
          "conditions": [],
          "level": 3,
          "trait": "gigani:crystalline_focus"
        },
        {
          "conditions": [],
          "level": 2,
          "trait": "gigani:resonant_lattice"
        },
        {
          "conditions": [],
          "level": 2,
          "trait": "gigani:waveform_harmonics"
        },
        {
          "conditions": [],
          "level": 1,
          "trait": "gigani:brittle_cleavage"
        },
        {
          "conditions": [],
          "level": 2,
          "trait": "gigani:matrix_bound"
        },
        {
          "conditions": [],
          "level": 1,
          "trait": "gigani:resonance_tuned"
        }
      ],
      "projectile_accuracy": {
        "operation": "MULTIPLY_TOTAL",
        "value": 0.02
      }
    },
    "silentgear:lining": {
      "armor_durability": {
        "operation": "MULTIPLY_BASE",
        "value": 0.056
      },
      "armor_toughness": {
        "operation": "ADD",
        "value": 0.705
      },
      "magic_armor": {
        "operation": "ADD",
        "value": 1.541
      },
      "traits": [
        {
          "conditions": [],
          "level": 2,
          "trait": "gigani:resonant_lattice"
        },
        {
          "conditions": [],
          "level": 3,
          "trait": "gigani:crystalline_focus"
        },
        {
          "conditions": [],
          "level": 1,
          "trait": "gigani:brittle_cleavage"
        },
        {
          "conditions": [],
          "level": 2,
          "trait": "gigani:waveform_harmonics"
        },
        {
          "conditions": [],
          "level": 2,
          "trait": "gigani:matrix_bound"
        },
        {
          "conditions": [],
          "level": 1,
          "trait": "gigani:resonance_tuned"
        }
      ]
    },
    "silentgear:cord": {
      "draw_speed": {
        "operation": "MULTIPLY_BASE",
        "value": 0.085
      },
      "projectile_speed": {
        "operation": "MULTIPLY_TOTAL",
        "value": 0.025
      },
      "ranged_damage": {
        "operation": "MULTIPLY_BASE",
        "value": 0.3
      },
      "traits": [
        {
          "conditions": [],
          "level": 2,
          "trait": "gigani:waveform_harmonics"
        },
        {
          "conditions": [],
          "level": 2,
          "trait": "gigani:resonant_lattice"
        },
        {
          "conditions": [],
          "level": 3,
          "trait": "gigani:crystalline_focus"
        },
        {
          "conditions": [],
          "level": 2,
          "trait": "gigani:matrix_bound"
        },
        {
          "conditions": [],
          "level": 1,
          "trait": "gigani:resonance_tuned"
        }
      ]
    },
    "silentgear:fletching": {
      "projectile_accuracy": 1.146,
      "projectile_speed": 1.044,
      "traits": [
        {
          "conditions": [],
          "level": 2,
          "trait": "gigani:waveform_harmonics"
        },
        {
          "conditions": [],
          "level": 3,
          "trait": "gigani:crystalline_focus"
        },
        {
          "conditions": [],
          "level": 2,
          "trait": "gigani:piezoelectric"
        },
        {
          "conditions": [],
          "level": 2,
          "trait": "gigani:matrix_bound"
        },
        {
          "conditions": [],
          "level": 1,
          "trait": "gigani:resonance_tuned"
        }
      ],
      "ranged_damage": {
        "operation": "ADD",
        "value": 1.383
      }
    }
  }
}
